textflowthon/__init__.py
textflowthon/core.py
textflowthon/fonts.py
textflowthon/utils.py
textflowthon/effects/__init__.py
textflowthon/effects/async_boot_sequence.py
textflowthon/effects/async_corrupt.py
textflowthon/effects/async_glitch.py
textflowthon/effects/async_marquee.py
textflowthon/effects/async_matrix_rain.py
textflowthon/effects/async_novice_type.py
textflowthon/effects/async_random_reveal.py
textflowthon/effects/async_reverse_typewrite.py
textflowthon/effects/async_typewrite.py
textflowthon/effects/boot_sequence.py
textflowthon/effects/corrupt.py
textflowthon/effects/glitch.py
textflowthon/effects/list_effects.py
textflowthon/effects/marquee.py
textflowthon/effects/matrix_rain.py
textflowthon/effects/novice_type.py
textflowthon/effects/rain_colors.py
textflowthon/effects/random_reveal.py
textflowthon/effects/reverse_typewrite.py
textflowthon/effects/typewrite.py
textflowthon-0.1.1.dist-info/METADATA
textflowthon-0.1.1.dist-info/WHEEL
textflowthon-0.1.1.dist-info/licenses/LICENSE
textflowthon-0.1.1.dist-info/RECORD
