Metadata-Version: 2.4
Name: textflowthon
Version: 0.1.1
Summary: A modular Python library for animating text output in the terminal with typewriter and other effects. Supports sync/async, custom fonts, and more.
Project-URL: Homepage, https://github.com/IAmNo1Special/textflowthon
Project-URL: Documentation, https://github.com/IAmNo1Special/textflowthon/blob/main/README.md
Project-URL: Repository, https://github.com/IAmNo1Special/textflowthon
Project-URL: Issues, https://github.com/IAmNo1Special/textflowthon/issues
Author-email: IAmNo1Special <IVmNo1Special@gmail.com>
License: MIT
License-File: LICENSE
Keywords: animation,async,console,effects,terminal,text,typewriter
Classifier: Development Status :: 3 - Alpha
Classifier: Intended Audience :: Developers
Classifier: License :: OSI Approved :: MIT License
Classifier: Operating System :: OS Independent
Classifier: Programming Language :: Python :: 3.12
Classifier: Programming Language :: Python :: 3.13
Classifier: Topic :: Software Development :: Libraries :: Python Modules
Classifier: Topic :: Terminals
Classifier: Topic :: Text Processing
Requires-Python: >=3.12
Requires-Dist: pyfiglet>=1.0.2
Requires-Dist: rich
Provides-Extra: docs
Requires-Dist: sphinx-autodoc-typehints>=1.26.0; extra == 'docs'
Requires-Dist: sphinx-rtd-theme>=1.3.0; extra == 'docs'
Requires-Dist: sphinx>=7.0.0; extra == 'docs'
Provides-Extra: test
Requires-Dist: pytest-asyncio>=0.26.0; extra == 'test'
Requires-Dist: pytest-cov>=4.1.0; extra == 'test'
Requires-Dist: pytest>=8.3.5; extra == 'test'
